chacha_cicd_helper/__init__.py
chacha_cicd_helper/__main__.py
chacha_cicd_helper/complexity_check.py
chacha_cicd_helper/coverage_tools.py
chacha_cicd_helper/doc_gen.py
chacha_cicd_helper/helper_base.py
chacha_cicd_helper/install_deps.py
chacha_cicd_helper/py.typed
chacha_cicd_helper/quality_check.py
chacha_cicd_helper/types_check.py
chacha_cicd_helper/unit_test.py
chacha_cicd_helper-0.4.dist-info/LICENSE.md
chacha_cicd_helper-0.4.dist-info/METADATA
chacha_cicd_helper-0.4.dist-info/WHEEL
chacha_cicd_helper-0.4.dist-info/top_level.txt
chacha_cicd_helper-0.4.dist-info/RECORD
