Metadata-Version: 2.1
Name: chacha_cicd_helper
Version: 0.4
Summary: A bundle of cicd helper tools
Author-email: chacha <1000CHACHA0001@gmail.com>
Maintainer-email: chacha <1000CHACHA0001@gmail.com>
License: # License
Project-URL: Homepage, https://chacha.ddns.net/gitea/chacha/chacha_cicd_helper
Project-URL: Documentation, https://chacha.ddns.net/mkdocs-web/chacha/chacha_cicd_helper/master/latest/
Project-URL: Tracker, https://chacha.ddns.net/gitea/chacha/chacha_cicd_helper/issues
Keywords: chacha,chacha,template,chacha_cicd_helper
Platform: any
Classifier: Development Status :: 4 - Beta
Classifier: Programming Language :: Python :: 3 :: Only
Classifier: Programming Language :: Python :: 3.9
Classifier: Programming Language :: Python :: 3.10
Classifier: Programming Language :: Python :: 3.11
Requires-Python: >=3.9
License-File: LICENSE.md
Requires-Dist: typed-argument-parser==1.*
Requires-Dist: packaging
Requires-Dist: junitparser>=2.8
Requires-Dist: junit2html>=30.1
Requires-Dist: xmlrunner>=1.7
Requires-Dist: mypy>=0.99
Requires-Dist: coverage>=7.0
Requires-Dist: radon>=5.1
Requires-Dist: pylint<3,>=2.15
Requires-Dist: pylint-json2html>=0.4
Requires-Dist: pandas>=1.5
Requires-Dist: mypy[reports]>=0.99
Requires-Dist: mkdocs>=1.4.0
Requires-Dist: mkdocs-material>=8.5
Requires-Dist: mkdocs-pymdownx-material-extras
Requires-Dist: mkdocs-localsearch>=0.9.0
Requires-Dist: mkdocstrings[python]>=0.19
Requires-Dist: mkdocs-with-pdf>=0.9.3
Requires-Dist: pyyaml>=6.0
Requires-Dist: pymdown-extensions>=9
Requires-Dist: mkdocs-markdownextradata-plugin
Requires-Dist: mkdocs-mermaid2-plugin
Requires-Dist: tomli; python_version < "3.11"
Requires-Dist: importlib-metadata; python_version < "3.9"
Provides-Extra: complexity-check
Requires-Dist: radon>=5.1; extra == "complexity-check"
Provides-Extra: coverage-check
Requires-Dist: coverage>=7.0; extra == "coverage-check"
Provides-Extra: doc-gen
Requires-Dist: mkdocs>=1.4.0; extra == "doc-gen"
Requires-Dist: mkdocs-material>=8.5; extra == "doc-gen"
Requires-Dist: mkdocs-pymdownx-material-extras; extra == "doc-gen"
Requires-Dist: mkdocs-localsearch>=0.9.0; extra == "doc-gen"
Requires-Dist: mkdocstrings[python]>=0.19; extra == "doc-gen"
Requires-Dist: mkdocs-with-pdf>=0.9.3; extra == "doc-gen"
Requires-Dist: pyyaml>=6.0; extra == "doc-gen"
Requires-Dist: pymdown-extensions>=9; extra == "doc-gen"
Requires-Dist: mkdocs-markdownextradata-plugin; extra == "doc-gen"
Requires-Dist: mkdocs-mermaid2-plugin; extra == "doc-gen"
Provides-Extra: quality-check
Requires-Dist: pylint<3,>=2.15; extra == "quality-check"
Requires-Dist: pylint-json2html>=0.4; extra == "quality-check"
Requires-Dist: pandas>=1.5; extra == "quality-check"
Requires-Dist: types-PyYAML; extra == "quality-check"
Provides-Extra: test
Requires-Dist: junitparser>=2.8; extra == "test"
Requires-Dist: junit2html>=30.1; extra == "test"
Requires-Dist: xmlrunner>=1.7; extra == "test"
Requires-Dist: mypy>=0.99; extra == "test"
Provides-Extra: type-check
Requires-Dist: mypy[reports]>=0.99; extra == "type-check"
